<virtual-user errorPolicy="DO_NOTHING"
    failedAssertionPolicy="DO_NOTHING" slaProfileEnabled="true" uid="PublicAPIs">
    <init-container element-number="1" execution-type="0" pacingEnd="0"
        pacingMode="MODE_NO_PACING" pacingStart="0" pacingValue="0"
        slaProfileEnabled="false" weightsEnabled="false">
        <description>Elements executed once when the Virtual User starts.</description>
        <weighted-embedded-action uid="6a143fd4-7ef7-425f-bb6f-74408ef90574"/>
    </init-container>
    <actions-container clearUserIterationDataMode="AUTO"
        element-number="1" execution-type="0" pacingEnd="0"
        pacingMode="MODE_PACING_SIMPLE" pacingStart="0" pacingValue="5"
        slaProfileEnabled="false" weightsEnabled="false">
        <description>Elements repeated until the Virtual User stops.</description>
        <weighted-embedded-action uid="e942700c-e807-4ffc-86f8-a474499485ca"/>
        <weighted-embedded-action uid="0caba07c-f2ba-409a-922a-92856579257a"/>
        <weighted-embedded-action uid="f9f096e6-4567-4326-9835-21b242367823"/>
        <weighted-embedded-action uid="0b518c10-5102-4a84-93b2-5ccc8cf153bd"/>
    </actions-container>
    <end-container element-number="1" execution-type="0" pacingEnd="0"
        pacingMode="MODE_NO_PACING" pacingStart="0" pacingValue="0"
        slaProfileEnabled="false" weightsEnabled="false">
        <description>Elements executed before the Virtual User stops.</description>
    </end-container>
    <thinktime-policy thinkTimeMode="MODE_SIMPLE_THINK_TIME"
        thinktimeFactorValue="100" thinktimePolicy="0"
        thinktimeRangeValue="0" thinktimeValue="5000"/>
</virtual-user>
