<http-page executeResourcesDynamically="false"
    name="/templates/main/posts/views/post-view.html_1"
    playRequestsSequentially="false"
    recordedArtifactZipFileName="team/vus/@post/%resources%/recorded-artifacts/46be7d22-cefa-4b15-855b-d83a84b4fb76.zip"
    slaProfileEnabled="false" thinkTime="0"
    thinkTimeMode="MODE_SIMPLE_THINK_TIME" thinkTimeRangeEnd=""
    thinkTimeRangeStart="" uid="46be7d22-cefa-4b15-855b-d83a84b4fb76">
    <embedded-action>d0f46b27-9553-4402-9187-d9e0d57e4343</embedded-action>
    <embedded-action>ce013867-02a4-4710-8760-cadf54a45f95</embedded-action>
    <screenshotFileDescription>recorded-screenshots/sc_28699eff-5521-4872-b42b-ec67afd581ff.jpg</screenshotFileDescription>
</http-page>
<http-action actionType="1" contentType="text/html"
    eTag="&quot;305-5418708f1ad80:dtagent10155181109122756i1Q3&quot;"
    extractorInjectPathPolicy="2" extractorPathPolicy="1"
    followRedirects="false" generatedByClient="false"
    linkExtractorSeveralMatchOccurrence="1"
    linkExtractorSeveralMatchPolicy="1" linkExtractorType="6"
    method="GET" name="/templates/main/posts/views/post-view.html"
    path="/templates/main/posts/views/post-view.html" postType="1"
    recordedArtifactZipFileName="team/vus/@post/%resources%/recorded-artifacts/46be7d22-cefa-4b15-855b-d83a84b4fb76.zip"
    recordedResponseCode="200" responseSize="773"
    serverUid="app_server_hostname" slaProfileEnabled="false"
    uid="d0f46b27-9553-4402-9187-d9e0d57e4343" useKeepAlive="false">
    <responsePageFileDescription>recorded-responses/res_fdcb9168-65b0-4a00-b91e-f37eef80a03f.html</responsePageFileDescription>
    <requestContentFileDescription>recorded-requests/req_fdcb9168-65b0-4a00-b91e-f37eef80a03f.txt</requestContentFileDescription>
    <header name="Accept" value="application/json, text/plain, */*"/>
    <header name="Accept-Encoding" value="gzip, deflate"/>
    <header name="Accept-Language" value="en-US,en;q=0.5"/>
    <header name="Connection" value="keep-alive"/>
    <header name="Cookie" value="dtCookie=2$1F7BDFF87E1D7DF431CD73A5698D1CD9; rxVisitor=1542032562278AKDH290BMTF09UEC3KHO6C3S75U62VJ5; rxvt=1542034365842|1542032090873; dtPC=2$32562269_51h1vGFKDJCKHLNNPPKAFIAFGJOGMEKILKJNP; dtSa=-; dtLatC=4"/>
    <header name="Host" value="ushahidi"/>
    <header name="Referer" value="http://ushahidi/views/map"/>
    <header name="User-Agent" value="Mozilla/5.0 (Macintosh; Intel Mac OS X 10.13; rv:63.0) Gecko/20100101 Firefox/63.0"/>
    <responseHeaders>HTTP/1.1 200 OK&#xd;
Date: Mon, 12 Nov 2018 14:22:45 GMT&#xd;
Server: Apache/2.4.25 (Debian)&#xd;
Last-Modified: Thu, 17 Nov 2016 22:51:49 GMT&#xd;
ETag: "305-5418708f1ad80:dtagent10155181025135642g0KY"&#xd;
Accept-Ranges: bytes&#xd;
X-OneAgent-JS-Injection: true&#xd;
X-ruxit-JS-Agent: true&#xd;
Vary: Accept-Encoding&#xd;
Content-Encoding: gzip&#xd;
Content-Length: 282&#xd;
Keep-Alive: timeout=5, max=97&#xd;
Connection: Keep-Alive&#xd;
Content-Type: text/html</responseHeaders>
    <record-html-infos extractorRegExp="false" htmlType="0"/>
</http-action>
<http-action actionType="1" contentType="application/json"
    extractorInjectPathPolicy="2" extractorPathPolicy="1"
    followRedirects="false" generatedByClient="false"
    linkExtractorSeveralMatchOccurrence="1"
    linkExtractorSeveralMatchPolicy="1" linkExtractorType="6"
    method="GET" name="/platform/api/v3/config/features"
    path="/platform/api/v3/config/features" postType="1"
    recordedArtifactZipFileName="team/vus/@post/%resources%/recorded-artifacts/46be7d22-cefa-4b15-855b-d83a84b4fb76.zip"
    recordedResponseCode="200" responseSize="730"
    serverUid="app_server_hostname" slaProfileEnabled="false"
    uid="ce013867-02a4-4710-8760-cadf54a45f95" useKeepAlive="false">
    <responsePageFileDescription>recorded-responses/res_e056f3fa-c9dd-476c-baec-73eba27dc5f3</responsePageFileDescription>
    <requestContentFileDescription>recorded-requests/req_e056f3fa-c9dd-476c-baec-73eba27dc5f3.txt</requestContentFileDescription>
    <header name="Accept" value="application/json, text/plain, */*"/>
    <header name="Accept-Encoding" value="gzip, deflate"/>
    <header name="Accept-Language" value="en-US,en;q=0.5"/>
    <header name="Authorization" value="Bearer ${oauth_bearer}"/>
    <header name="Connection" value="keep-alive"/>
    <header name="Cookie" value="dtCookie=2$1F7BDFF87E1D7DF431CD73A5698D1CD9; rxVisitor=1542032562278AKDH290BMTF09UEC3KHO6C3S75U62VJ5; rxvt=1542034365842|1542032090873; dtPC=2$32562269_51h1vGFKDJCKHLNNPPKAFIAFGJOGMEKILKJNP; dtSa=-; dtLatC=4"/>
    <header name="Host" value="ushahidi"/>
    <header name="Referer" value="http://ushahidi/views/map"/>
    <header name="User-Agent" value="Mozilla/5.0 (Macintosh; Intel Mac OS X 10.13; rv:63.0) Gecko/20100101 Firefox/63.0"/>
    <responseHeaders>HTTP/1.1 200 OK&#xd;
Date: Mon, 12 Nov 2018 14:22:46 GMT&#xd;
Server: Apache/2.4.25 (Debian)&#xd;
X-Powered-By: PHP/7.0.31&#xd;
Access-Control-Allow-Origin: *&#xd;
Access-Control-Allow-Headers: Authorization, Content-type&#xd;
Allow: GET, PUT, OPTIONS&#xd;
Access-Control-Allow-Methods: GET, PUT, OPTIONS&#xd;
Content-Length: 730&#xd;
Keep-Alive: timeout=5, max=100&#xd;
Connection: Keep-Alive&#xd;
Content-Type: application/json</responseHeaders>
    <record-html-infos extractorRegExp="false" htmlType="0"/>
</http-action>
